deepctr/__init__.py
deepctr/feature_column.py
deepctr/inputs.py
deepctr/utils.py
deepctr/contrib/__init__.py
deepctr/contrib/rnn.py
deepctr/contrib/rnn_v2.py
deepctr/contrib/utils.py
deepctr/estimator/__init__.py
deepctr/estimator/feature_column.py
deepctr/estimator/inputs.py
deepctr/estimator/utils.py
deepctr/estimator/models/__init__.py
deepctr/estimator/models/afm.py
deepctr/estimator/models/autoint.py
deepctr/estimator/models/ccpm.py
deepctr/estimator/models/dcn.py
deepctr/estimator/models/deepfefm.py
deepctr/estimator/models/deepfm.py
deepctr/estimator/models/fibinet.py
deepctr/estimator/models/fnn.py
deepctr/estimator/models/fwfm.py
deepctr/estimator/models/nfm.py
deepctr/estimator/models/pnn.py
deepctr/estimator/models/wdl.py
deepctr/estimator/models/xdeepfm.py
deepctr/layers/__init__.py
deepctr/layers/activation.py
deepctr/layers/core.py
deepctr/layers/interaction.py
deepctr/layers/normalization.py
deepctr/layers/sequence.py
deepctr/layers/utils.py
deepctr/models/__init__.py
deepctr/models/afm.py
deepctr/models/autoint.py
deepctr/models/ccpm.py
deepctr/models/dcn.py
deepctr/models/dcnmix.py
deepctr/models/deepfefm.py
deepctr/models/deepfm.py
deepctr/models/difm.py
deepctr/models/edcn.py
deepctr/models/fgcnn.py
deepctr/models/fibinet.py
deepctr/models/flen.py
deepctr/models/fnn.py
deepctr/models/fwfm.py
deepctr/models/ifm.py
deepctr/models/mlr.py
deepctr/models/nfm.py
deepctr/models/onn.py
deepctr/models/pnn.py
deepctr/models/wdl.py
deepctr/models/xdeepfm.py
deepctr/models/multitask/__init__.py
deepctr/models/multitask/esmm.py
deepctr/models/multitask/mmoe.py
deepctr/models/multitask/ple.py
deepctr/models/multitask/sharedbottom.py
deepctr/models/sequence/__init__.py
deepctr/models/sequence/bst.py
deepctr/models/sequence/dien.py
deepctr/models/sequence/din.py
deepctr/models/sequence/dsin.py
deepctr-0.9.3.dist-info/LICENSE
deepctr-0.9.3.dist-info/METADATA
deepctr-0.9.3.dist-info/WHEEL
deepctr-0.9.3.dist-info/top_level.txt
deepctr-0.9.3.dist-info/RECORD
