Metadata-Version: 2.1
Name: deepctr
Version: 0.9.3
Summary: Easy-to-use,Modular and Extendible package of deep learning based CTR(Click Through Rate) prediction models with tensorflow 1.x and 2.x .
Home-page: https://github.com/shenweichen/deepctr
Author: Weichen Shen
Author-email: weichenswc@163.com
License: Apache-2.0
Download-URL: https://github.com/shenweichen/deepctr/tags
Keywords: ctr,click through rate,deep learning,tensorflow,tensor,keras
Platform: UNKNOWN
Classifier: License :: OSI Approved :: Apache Software License
Classifier: Operating System :: OS Independent
Classifier: Intended Audience :: Developers
Classifier: Intended Audience :: Education
Classifier: Intended Audience :: Science/Research
Classifier: Programming Language :: Python :: 3
Classifier: Programming Language :: Python :: 2.7
Classifier: Programming Language :: Python :: 3.6
Classifier: Programming Language :: Python :: 3.7
Classifier: Programming Language :: Python :: 3.8
Classifier: Programming Language :: Python :: 3.9
Classifier: Programming Language :: Python :: 3.10
Classifier: Topic :: Scientific/Engineering
Classifier: Topic :: Scientific/Engineering :: Artificial Intelligence
Classifier: Topic :: Software Development
Classifier: Topic :: Software Development :: Libraries
Classifier: Topic :: Software Development :: Libraries :: Python Modules
Requires-Python: >=2.7,!=3.0.*,!=3.1.*,!=3.2.*,!=3.3.*,!=3.4.*
Requires-Dist: requests
Requires-Dist: h5py (==2.10.0) ; python_version < "3.9"
Requires-Dist: h5py (==3.7.0) ; python_version >= "3.9"
Provides-Extra: cpu
Requires-Dist: tensorflow (!=1.7.*,!=1.8.*,>=1.4.0) ; extra == 'cpu'
Provides-Extra: gpu
Requires-Dist: tensorflow-gpu (!=1.7.*,!=1.8.*,>=1.4.0) ; extra == 'gpu'
